[
    {
        "model": "auth.user",
        "pk": 1,
        "fields": {
            "first_name": "Jonathan",
            "last_name": "VanDuyne",
            "email": "jonathanislame@aol.com",
            "username": "jonathanislame@aol.com",
            "password": "pbkdf2_sha256$320000$L9WyeeE95squbRZelePsZf$XayBzPujv5CeAnmIzcLL0orBqE3qDpJLuQsy9zOM5rc=",
            "is_staff": true
        }
    },
    {
        "model": "auth.user",
        "pk": 2,
        "fields": {
            "first_name": "Cassie",
            "last_name": "Revell",
            "email": "cassie@catz.com",
            "username": "cassie@catz.com",
            "password": "pbkdf2_sha256$320000$L9WyeeE95squbRZelePsZf$XayBzPujv5CeAnmIzcLL0orBqE3qDpJLuQsy9zOM5rc=",
            "is_staff": true
        }
    },
    {
        "model": "auth.user",
        "pk": 3,
        "fields": {
            "first_name": "Chesney",
            "last_name": "Hardin",
            "email": "chesney@farmersmeet.com",
            "username": "chesney@farmersmeet.com",
            "password": "pbkdf2_sha256$320000$L9WyeeE95squbRZelePsZf$XayBzPujv5CeAnmIzcLL0orBqE3qDpJLuQsy9zOM5rc=",
            "is_staff": false
        }
    },
    {
        "model": "auth.user",
        "pk": 4,
        "fields": {
            "first_name": "Daniel",
            "last_name": "Myers",
            "email": "danielmyers@queue.com",
            "username": "danielmyers@queue.com",
            "password": "pbkdf2_sha256$320000$L9WyeeE95squbRZelePsZf$XayBzPujv5CeAnmIzcLL0orBqE3qDpJLuQsy9zOM5rc=",
            "is_staff": false
        }
    },
    {
        "model": "auth.user",
        "pk": 5,
        "fields": {
            "password": "pbkdf2_sha256$320000$L9WyeeE95squbRZelePsZf$XayBzPujv5CeAnmIzcLL0orBqE3qDpJLuQsy9zOM5rc=",
            "last_login": null,
            "is_superuser": false,
            "username": "emily@lemmon.com",
            "first_name": "Emily",
            "last_name": "Lemmon",
            "email": "emily@lemmon.com",
            "is_staff": true,
            "is_active": true
        }
    }
]